aiida_bigdft/__init__.py
aiida_bigdft/calculations.py
aiida_bigdft/cli.py
aiida_bigdft/helpers.py
aiida_bigdft/parsers.py
aiida_bigdft/data/BigDFTFile.py
aiida_bigdft/data/BigDFTParameters.py
aiida_bigdft/data/__init__.py
aiida_bigdft/utils/MiniLogger.py
aiida_bigdft/utils/__init__.py
aiida_bigdft/workflows/__init__.py
aiida_bigdft/workflows/base.py
aiida_bigdft-0.3.0.dist-info/entry_points.txt
aiida_bigdft-0.3.0.dist-info/LICENSE
aiida_bigdft-0.3.0.dist-info/WHEEL
aiida_bigdft-0.3.0.dist-info/METADATA
aiida_bigdft-0.3.0.dist-info/RECORD
