Metadata-Version: 2.1
Name: aiida-bigdft
Version: 0.3.0
Summary: Translation layer for AiiDA-PyBigDFT
Keywords: aiida,plugin
Author-email: Louis Beal <louis.j.beal@gmail.com>
Requires-Python: >=3.7
Classifier: Programming Language :: Python
Classifier: Intended Audience :: Science/Research
Classifier: License :: OSI Approved :: MIT License
Classifier: Natural Language :: English
Classifier: Development Status :: 3 - Alpha
Classifier: Framework :: AiiDA
Requires-Dist: aiida-core>=1.6.3,<3
Requires-Dist: voluptuous
Requires-Dist: PyBigDFT
Requires-Dist: ase
Requires-Dist: click
Requires-Dist: sphinx ; extra == "docs"
Requires-Dist: sphinxcontrib-contentui ; extra == "docs"
Requires-Dist: sphinxcontrib-details-directive ; extra == "docs"
Requires-Dist: furo ; extra == "docs"
Requires-Dist: markupsafe<2.1 ; extra == "docs"
Requires-Dist: pre-commit~=2.2 ; extra == "pre-commit"
Requires-Dist: pylint~=2.15.10 ; extra == "pre-commit"
Requires-Dist: pgtest~=1.3.1 ; extra == "testing"
Requires-Dist: wheel~=0.31 ; extra == "testing"
Requires-Dist: coverage[toml] ; extra == "testing"
Requires-Dist: pytest~=6.0 ; extra == "testing"
Requires-Dist: pytest-cov ; extra == "testing"
Project-URL: Source, https://github.com/ljbeal/aiida-bigdft
Provides-Extra: docs
Provides-Extra: pre-commit
Provides-Extra: testing
